pylists/__init__.py
pylists-0.0.1.4.dist-info/METADATA
pylists-0.0.1.4.dist-info/WHEEL
pylists-0.0.1.4.dist-info/top_level.txt
pylists-0.0.1.4.dist-info/RECORD
