Metadata-Version: 2.1
Name: pylists
Version: 0.0.1.4
Summary: Lists
Home-page: https://github.com/DOG-E
Author: DOG-E
Author-email: DogeUserBot@gmail.com
License: UNKNOWN
Platform: UNKNOWN
Classifier: Operating System :: OS Independent
Classifier: Programming Language :: Python :: 3
Classifier: Programming Language :: Python :: 2
